{
  "definitions": [
    {
      "title": "Fragment",
      "id": "fragment",
      "model": "fragment",
      "plugins": {
        "da": {
          "unsafeHTML": "<p><a href=\"/fragments/\">/fragments/</a></p>",
          "fields": [
            { "name": "content", "selector": "div" }
          ]
        }
      }
    }
  ],
  "models": [
    {
      "id": "fragment",
      "fields": [
        {
          "component": "richtext",
          "name": "content",
          "label": "Fragment Link",
          "description": "Add a link to a fragment path (e.g. /fragments/nav/header)",
          "valueType": "string"
        }
      ]
    }
  ],
  "filters": []
}
